brocc-1.4.0.data/scripts/brocc.py
brocc-1.4.0.data/scripts/compare_brocc_assignments.py
brocc-1.4.0.data/scripts/create_local_taxonomy_db.py
brocc-1.4.0.dist-info/METADATA
brocc-1.4.0.dist-info/RECORD
brocc-1.4.0.dist-info/WHEEL
brocc-1.4.0.dist-info/top_level.txt
brocclib/__init__.py
brocclib/assign.py
brocclib/command.py
brocclib/get_xml.py
brocclib/parse.py
brocclib/taxonomy.py
brocclib/taxonomy_db.py
