Metadata-Version: 2.1
Name: brocc
Version: 1.4.0
Summary: BLAST READ and OTU Consensus Classifier
Home-page: https://github.com/kylebittinger/brocc
Author: Serena Dollive, Kyle Bittinger
Author-email: kylebittinger@gmail.com
Maintainer: Kyle Bittinger
Maintainer-email: kylebittinger@gmail.com
License: UNKNOWN
Platform: UNKNOWN
Classifier: Programming Language :: Python :: 3
Classifier: License :: OSI Approved :: GNU General Public License v2 (GPLv2)
Classifier: Topic :: Scientific/Engineering :: Bio-Informatics
